pyrouteplanner/__init__.py
pyrouteplanner/static/css/main.css
pyrouteplanner/static/js/geo.js
pyrouteplanner/static/js/mapController.js
pyrouteplanner/static/js/ui.js
pyrouteplanner/static/vendor/leaflet-src.esm.js
pyrouteplanner/static/vendor/leaflet-src.esm.js.map
pyrouteplanner/static/vendor/leaflet-src.js
pyrouteplanner/static/vendor/leaflet-src.js.map
pyrouteplanner/static/vendor/leaflet.css
pyrouteplanner/static/vendor/leaflet.js
pyrouteplanner/static/vendor/leaflet.js.map
pyrouteplanner/static/vendor/images/layers-2x.png
pyrouteplanner/static/vendor/images/layers.png
pyrouteplanner/static/vendor/images/marker-icon-2x.png
pyrouteplanner/static/vendor/images/marker-icon.png
pyrouteplanner/static/vendor/images/marker-shadow.png
pyrouteplanner/templates/index.html
pyrouteplanner-1.0.5.dist-info/licenses/LICENSE.txt
pyrouteplanner-1.0.5.dist-info/METADATA
pyrouteplanner-1.0.5.dist-info/WHEEL
pyrouteplanner-1.0.5.dist-info/entry_points.txt
pyrouteplanner-1.0.5.dist-info/top_level.txt
pyrouteplanner-1.0.5.dist-info/RECORD
