Metadata-Version: 2.4
Name: pyrouteplanner
Version: 1.0.5
Summary: Flask server, leaflet.js-based route planner
Author-email: Emmet Weyman <emmetweyman@vt.edu>
License:                     GNU GENERAL PUBLIC LICENSE
Requires-Python: >=3.11
License-File: LICENSE.txt
Requires-Dist: flask>=3.1.2
Dynamic: license-file
